[
  {
    "id": "ic_001",
    "type": "ayah",
    "arabicText": "وَمَن يَتَوَكَّلْ عَلَى اللَّهِ فَهُوَ حَسْبُهُ",
    "banglaTransliteration": "ওয়া মাইঁ ইয়াতাওয়াক্কাল আলাল্লাহি ফাহুয়া হাসবুহু",
    "banglaTranslation": "যে ব্যক্তি আল্লাহর উপর ভরসা করে, তার জন্য আল্লাহই যথেষ্ট।",
    "source": "সূরা তালাক, আয়াত ৩",
    "topic": "tawakkul",
    "duaCategory": null,
    "stepAssignment": 1,
    "relatedContentIds": ["ic_002", "ic_003"]
  },
  {
    "id": "ic_002",
    "type": "hadith",
    "arabicText": "احْرِصْ عَلَى مَا يَنْفَعُكَ وَاسْتَعِنْ بِاللَّهِ وَلَا تَعْجَزْ",
    "banglaTransliteration": "ইহরিস আলা মা ইয়ানফাউকা ওয়াস্তাইন বিল্লাহি ওয়ালা তা'জায",
    "banglaTranslation": "যা তোমার উপকার করে তার প্রতি আগ্রহী হও, আল্লাহর সাহায্য চাও এবং অক্ষম হয়ো না।",
    "source": "সহিহ মুসলিম, হাদিস ২৬৬৪",
    "topic": "tawakkul",
    "duaCategory": null,
    "stepAssignment": 2,
    "relatedContentIds": ["ic_001", "ic_004"]
  },
  {
    "id": "ic_003",
    "type": "ayah",
    "arabicText": "وَعَلَى اللَّهِ فَتَوَكَّلُوا إِن كُنتُم مُّؤْمِنِينَ",
    "banglaTransliteration": "ওয়া আলাল্লাহি ফাতাওয়াক্কালু ইন কুনতুম মু'মিনিন",
    "banglaTranslation": "আর আল্লাহর উপরই ভরসা করো যদি তোমরা মুমিন হও।",
    "source": "সূরা মায়িদা, আয়াত ২৩",
    "topic": "tawakkul",
    "duaCategory": null,
    "stepAssignment": 3,
    "relatedContentIds": ["ic_001", "ic_005"]
  },
  {
    "id": "ic_004",
    "type": "ayah",
    "arabicText": "أَلَا بِذِكْرِ اللَّهِ تَطْمَئِنُّ الْقُلُوبُ",
    "banglaTransliteration": "আলা বিযিকরিল্লাহি তাতমাইন্নুল কুলুব",
    "banglaTranslation": "জেনে রাখো, আল্লাহর স্মরণেই অন্তরসমূহ প্রশান্তি লাভ করে।",
    "source": "সূরা রাদ, আয়াত ২৮",
    "topic": "tawakkul",
    "duaCategory": null,
    "stepAssignment": 4,
    "relatedContentIds": ["ic_003", "ic_006"]
  },
  {
    "id": "ic_005",
    "type": "hadith",
    "arabicText": "لَوْ أَنَّكُمْ كُنْتُمْ تَوَكَّلُونَ عَلَى اللَّهِ حَقَّ تَوَكُّلِهِ لَرُزِقْتُمْ كَمَا يُرْزَقُ الطَّيْرُ",
    "banglaTransliteration": "লাও আন্নাকুম কুনতুম তাওয়াক্কালুনা আলাল্লাহি হাক্কা তাওয়াক্কুলিহি লারুযিকতুম কামা ইউরযাকুত তাইর",
    "banglaTranslation": "যদি তোমরা আল্লাহর উপর যথাযথভাবে ভরসা করতে, তাহলে তিনি তোমাদের রিযিক দিতেন যেভাবে পাখিকে দেন।",
    "source": "তিরমিযি, হাদিস ২৩৪৪",
    "topic": "tawakkul",
    "duaCategory": null,
    "stepAssignment": 5,
    "relatedContentIds": ["ic_002", "ic_007"]
  },
  {
    "id": "ic_006",
    "type": "ayah",
    "arabicText": "إِنَّ اللَّهَ يُحِبُّ الْمُتَوَكِّلِينَ",
    "banglaTransliteration": "ইন্নাল্লাহা ইউহিব্বুল মুতাওয়াক্কিলিন",
    "banglaTranslation": "নিশ্চয়ই আল্লাহ তাওয়াক্কুলকারীদের ভালোবাসেন।",
    "source": "সূরা আলে ইমরান, আয়াত ১৫৯",
    "topic": "tawakkul",
    "duaCategory": null,
    "stepAssignment": 6,
    "relatedContentIds": ["ic_004", "ic_005"]
  },
  {
    "id": "ic_007",
    "type": "ayah",
    "arabicText": "وَمَن يَتَّقِ اللَّهَ يَجْعَل لَّهُ مَخْرَجًا وَيَرْزُقْهُ مِنْ حَيْثُ لَا يَحْتَسِبُ",
    "banglaTransliteration": "ওয়া মাইঁ ইয়াত্তাকিল্লাহা ইয়াজআল লাহু মাখরাজা ওয়া ইয়ারযুকহু মিন হাইসু লা ইয়াহতাসিব",
    "banglaTranslation": "যে আল্লাহকে ভয় করে, তিনি তার জন্য পথ বের করে দেন এবং তাকে এমন জায়গা থেকে রিযিক দেন যা সে কল্পনাও করেনি।",
    "source": "সূরা তালাক, আয়াত ২-৩",
    "topic": "tawakkul",
    "duaCategory": null,
    "stepAssignment": 7,
    "relatedContentIds": ["ic_001", "ic_006"]
  },
  {
    "id": "ic_008",
    "type": "ayah",
    "arabicText": "يَا أَيُّهَا الَّذِينَ آمَنُوا اسْتَعِينُوا بِالصَّبْرِ وَالصَّلَاةِ إِنَّ اللَّهَ مَعَ الصَّابِرِينَ",
    "banglaTransliteration": "ইয়া আইয়্যুহাল্লাযিনা আমানুস তাইনু বিস সাবরি ওয়াস সালাহ ইন্নাল্লাহা মাআস সাবিরিন",
    "banglaTranslation": "হে মুমিনগণ! ধৈর্য ও নামাজের মাধ্যমে সাহায্য চাও। নিশ্চয়ই আল্লাহ ধৈর্যশীলদের সাথে আছেন।",
    "source": "সূরা বাকারা, আয়াত ১৫৩",
    "topic": "sabr",
    "duaCategory": null,
    "stepAssignment": 8,
    "relatedContentIds": ["ic_009", "ic_011"]
  },
  {
    "id": "ic_009",
    "type": "ayah",
    "arabicText": "فَإِنَّ مَعَ الْعُسْرِ يُسْرًا إِنَّ مَعَ الْعُسْرِ يُسْرًا",
    "banglaTransliteration": "ফাইন্না মাআল উসরি ইউসরা, ইন্না মাআল উসরি ইউসরা",
    "banglaTranslation": "নিশ্চয়ই কষ্টের সাথে স্বস্তি আছে। নিশ্চয়ই কষ্টের সাথে স্বস্তি আছে।",
    "source": "সূরা ইনশিরাহ, আয়াত ৫-৬",
    "topic": "sabr",
    "duaCategory": null,
    "stepAssignment": 9,
    "relatedContentIds": ["ic_008", "ic_010"]
  },
  {
    "id": "ic_010",
    "type": "hadith",
    "arabicText": "مَا أُعْطِيَ أَحَدٌ عَطَاءً خَيْرًا وَأَوْسَعَ مِنَ الصَّبْرِ",
    "banglaTransliteration": "মা উতিয়া আহাদুন আতাআন খাইরান ওয়া আওসাআ মিনাস সাবর",
    "banglaTranslation": "ধৈর্যের চেয়ে উত্তম ও প্রশস্ত কোনো দান কাউকে দেওয়া হয়নি।",
    "source": "সহিহ বুখারি, হাদিস ১৪৬৯",
    "topic": "sabr",
    "duaCategory": null,
    "stepAssignment": 10,
    "relatedContentIds": ["ic_008", "ic_012"]
  },
  {
    "id": "ic_011",
    "type": "ayah",
    "arabicText": "وَلَنَبْلُوَنَّكُم بِشَيْءٍ مِّنَ الْخَوْفِ وَالْجُوعِ وَنَقْصٍ مِّنَ الْأَمْوَالِ وَالْأَنفُسِ وَالثَّمَرَاتِ وَبَشِّرِ الصَّابِرِينَ",
    "banglaTransliteration": "ওয়া লানাবলুওয়ান্নাকুম বিশাইয়িম মিনাল খাওফি ওয়াল জুই ওয়া নাকসিম মিনাল আমওয়ালি ওয়াল আনফুসি ওয়াস সামারাত ওয়া বাশশিরিস সাবিরিন",
    "banglaTranslation": "আমি অবশ্যই তোমাদের পরীক্ষা করব কিছু ভয়, ক্ষুধা, সম্পদ ও জীবনের ক্ষতি দিয়ে। আর ধৈর্যশীলদের সুসংবাদ দাও।",
    "source": "সূরা বাকারা, আয়াত ১৫৫",
    "topic": "sabr",
    "duaCategory": null,
    "stepAssignment": 11,
    "relatedContentIds": ["ic_008", "ic_013"]
  },
  {
    "id": "ic_012",
    "type": "ayah",
    "arabicText": "إِنَّمَا يُوَفَّى الصَّابِرُونَ أَجْرَهُم بِغَيْرِ حِسَابٍ",
    "banglaTransliteration": "ইন্নামা ইউওয়াফ্ফাস সাবিরুনা আজরাহুম বিগাইরি হিসাব",
    "banglaTranslation": "ধৈর্যশীলদের পুরস্কার অগণিতভাবে দেওয়া হবে।",
    "source": "সূরা যুমার, আয়াত ১০",
    "topic": "sabr",
    "duaCategory": null,
    "stepAssignment": 12,
    "relatedContentIds": ["ic_010", "ic_014"]
  },
  {
    "id": "ic_013",
    "type": "hadith",
    "arabicText": "عَجَبًا لِأَمْرِ الْمُؤْمِنِ إِنَّ أَمْرَهُ كُلَّهُ خَيْرٌ وَلَيْسَ ذَاكَ لِأَحَدٍ إِلَّا لِلْمُؤْمِنِ",
    "banglaTransliteration": "আজাবান লিআমরিল মু'মিন ইন্না আমরাহু কুল্লাহু খাইর ওয়া লাইসা যালিকা লিআহাদিন ইল্লা লিলমু'মিন",
    "banglaTranslation": "মুমিনের বিষয়টি আশ্চর্যজনক! তার সব বিষয়ই কল্যাণকর। এটি শুধু মুমিনের জন্যই।",
    "source": "সহিহ মুসলিম, হাদিস ২৯৯৯",
    "topic": "sabr",
    "duaCategory": null,
    "stepAssignment": 13,
    "relatedContentIds": ["ic_011", "ic_012"]
  },
  {
    "id": "ic_014",
    "type": "ayah",
    "arabicText": "وَاصْبِرْ وَمَا صَبْرُكَ إِلَّا بِاللَّهِ",
    "banglaTransliteration": "ওয়াসবির ওয়া মা সাবরুকা ইল্লা বিল্লাহ",
    "banglaTranslation": "ধৈর্য ধারণ করো এবং তোমার ধৈর্য তো শুধু আল্লাহর সাহায্যেই সম্ভব।",
    "source": "সূরা নাহল, আয়াত ১২৭",
    "topic": "sabr",
    "duaCategory": null,
    "stepAssignment": 14,
    "relatedContentIds": ["ic_008", "ic_013"]
  },
  {
    "id": "ic_015",
    "type": "ayah",
    "arabicText": "وَأَمَّا مَنْ خَافَ مَقَامَ رَبِّهِ وَنَهَى النَّفْسَ عَنِ الْهَوَىٰ فَإِنَّ الْجَنَّةَ هِيَ الْمَأْوَىٰ",
    "banglaTransliteration": "ওয়া আম্মা মান খাফা মাকামা রাব্বিহি ওয়া নাহান নাফসা আনিল হাওয়া ফাইন্নাল জান্নাতা হিয়াল মা'ওয়া",
    "banglaTranslation": "আর যে তার প্রতিপালকের সামনে দাঁড়ানোকে ভয় করে এবং নিজের প্রবৃত্তিকে নিয়ন্ত্রণ করে, তার আবাস হবে জান্নাত।",
    "source": "সূরা আন-নাযিয়াত, আয়াত ৪০-৪১",
    "topic": "self_control",
    "duaCategory": null,
    "stepAssignment": 15,
    "relatedContentIds": ["ic_016", "ic_019"]
  },
  {
    "id": "ic_016",
    "type": "hadith",
    "arabicText": "لَيْسَ الشَّدِيدُ بِالصُّرَعَةِ إِنَّمَا الشَّدِيدُ الَّذِي يَمْلِكُ نَفْسَهُ عِنْدَ الْغَضَبِ",
    "banglaTransliteration": "লাইসাশ শাদিদু বিস সুরআতি ইন্নামাশ শাদিদুল্লাযি ইয়ামলিকু নাফসাহু ইন্দাল গাদাব",
    "banglaTranslation": "শক্তিশালী সে নয় যে কুস্তিতে জেতে, বরং শক্তিশালী সে যে রাগের সময় নিজেকে নিয়ন্ত্রণ করতে পারে।",
    "source": "সহিহ বুখারি, হাদিস ৬১১৪",
    "topic": "self_control",
    "duaCategory": null,
    "stepAssignment": 16,
    "relatedContentIds": ["ic_015", "ic_017"]
  },
  {
    "id": "ic_017",
    "type": "ayah",
    "arabicText": "وَالَّذِينَ جَاهَدُوا فِينَا لَنَهْدِيَنَّهُمْ سُبُلَنَا",
    "banglaTransliteration": "ওয়াল্লাযিনা জাহাদু ফিনা লানাহদিয়ান্নাহুম সুবুলানা",
    "banglaTranslation": "যারা আমার পথে সংগ্রাম করে, আমি অবশ্যই তাদের আমার পথ দেখাব।",
    "source": "সূরা আনকাবুত, আয়াত ৬৯",
    "topic": "self_control",
    "duaCategory": null,
    "stepAssignment": 17,
    "relatedContentIds": ["ic_015", "ic_018"]
  },
  {
    "id": "ic_018",
    "type": "hadith",
    "arabicText": "مَنْ صَامَ يَوْمًا فِي سَبِيلِ اللَّهِ بَاعَدَ اللَّهُ وَجْهَهُ عَنِ النَّارِ سَبْعِينَ خَرِيفًا",
    "banglaTransliteration": "মান সামা ইয়াওমান ফি সাবিলিল্লাহি বাআদাল্লাহু ওয়াজহাহু আনিন নারি সাবইনা খারিফা",
    "banglaTranslation": "যে ব্যক্তি আল্লাহর পথে একদিন রোজা রাখে, আল্লাহ তার মুখকে জাহান্নাম থেকে সত্তর বছরের দূরত্বে রাখেন।",
    "source": "সহিহ বুখারি, হাদিস ২৮৪০",
    "topic": "self_control",
    "duaCategory": null,
    "stepAssignment": 18,
    "relatedContentIds": ["ic_016", "ic_020"]
  },
  {
    "id": "ic_019",
    "type": "ayah",
    "arabicText": "إِنَّ النَّفْسَ لَأَمَّارَةٌ بِالسُّوءِ إِلَّا مَا رَحِمَ رَبِّي",
    "banglaTransliteration": "ইন্নান নাফসা লাআম্মারাতুম বিস সু'ই ইল্লা মা রাহিমা রাব্বি",
    "banglaTranslation": "নিশ্চয়ই নফস মন্দের দিকে প্রবলভাবে আদেশ করে, তবে আমার প্রতিপালক যার উপর রহম করেন সে ছাড়া।",
    "source": "সূরা ইউসুফ, আয়াত ৫৩",
    "topic": "self_control",
    "duaCategory": null,
    "stepAssignment": 19,
    "relatedContentIds": ["ic_015", "ic_021"]
  },
  {
    "id": "ic_020",
    "type": "hadith",
    "arabicText": "إِنَّ اللَّهَ كَتَبَ الْإِحْسَانَ عَلَى كُلِّ شَيْءٍ",
    "banglaTransliteration": "ইন্নাল্লাহা কাতাবাল ইহসানা আলা কুল্লি শাই",
    "banglaTranslation": "নিশ্চয়ই আল্লাহ প্রতিটি বিষয়ে সুন্দরভাবে করার নির্দেশ দিয়েছেন।",
    "source": "সহিহ মুসলিম, হাদিস ১৯৫৫",
    "topic": "self_control",
    "duaCategory": null,
    "stepAssignment": 20,
    "relatedContentIds": ["ic_018", "ic_019"]
  },
  {
    "id": "ic_021",
    "type": "ayah",
    "arabicText": "قَدْ أَفْلَحَ مَن زَكَّاهَا وَقَدْ خَابَ مَن دَسَّاهَا",
    "banglaTransliteration": "কাদ আফলাহা মান যাক্কাহা ওয়া কাদ খাবা মান দাস্সাহা",
    "banglaTranslation": "সে সফল হয়েছে যে নিজেকে পরিশুদ্ধ করেছে এবং সে ব্যর্থ হয়েছে যে নিজেকে কলুষিত করেছে।",
    "source": "সূরা শামস, আয়াত ৯-১০",
    "topic": "self_control",
    "duaCategory": null,
    "stepAssignment": 21,
    "relatedContentIds": ["ic_015", "ic_019"]
  },
  {
    "id": "ic_022",
    "type": "ayah",
    "arabicText": "لَئِن شَكَرْتُمْ لَأَزِيدَنَّكُمْ",
    "banglaTransliteration": "লাইন শাকারতুম লাআযিদান্নাকুম",
    "banglaTranslation": "যদি তোমরা কৃতজ্ঞ হও, তাহলে আমি অবশ্যই তোমাদের আরও বাড়িয়ে দেব।",
    "source": "সূরা ইব্রাহিম, আয়াত ৭",
    "topic": "health",
    "duaCategory": null,
    "stepAssignment": 22,
    "relatedContentIds": ["ic_023", "ic_030"]
  },
  {
    "id": "ic_023",
    "type": "hadith",
    "arabicText": "نِعْمَتَانِ مَغْبُونٌ فِيهِمَا كَثِيرٌ مِنَ النَّاسِ الصِّحَّةُ وَالْفَرَاغُ",
    "banglaTransliteration": "নিআমাতানি মাগবুনুন ফিহিমা কাসিরুম মিনান নাসি আস সিহহাতু ওয়াল ফারাগ",
    "banglaTranslation": "দুটি নেয়ামত সম্পর্কে অধিকাংশ মানুষ ক্ষতিগ্রস্ত: সুস্বাস্থ্য এবং অবসর সময়।",
    "source": "সহিহ বুখারি, হাদিস ৬৪১২",
    "topic": "health",
    "duaCategory": null,
    "stepAssignment": 23,
    "relatedContentIds": ["ic_022", "ic_024"]
  },
  {
    "id": "ic_024",
    "type": "hadith",
    "arabicText": "إِنَّ لِجَسَدِكَ عَلَيْكَ حَقًّا",
    "banglaTransliteration": "ইন্না লিজাসাদিকা আলাইকা হাক্কা",
    "banglaTranslation": "নিশ্চয়ই তোমার শরীরের তোমার উপর অধিকার আছে।",
    "source": "সহিহ বুখারি, হাদিস ১৯৭৫",
    "topic": "health",
    "duaCategory": null,
    "stepAssignment": 24,
    "relatedContentIds": ["ic_023", "ic_025"]
  },
  {
    "id": "ic_025",
    "type": "ayah",
    "arabicText": "وَلَا تُلْقُوا بِأَيْدِيكُمْ إِلَى التَّهْلُكَةِ",
    "banglaTransliteration": "ওয়া লা তুলকু বিআইদিকুম ইলাত তাহলুকাহ",
    "banglaTranslation": "নিজেদের হাতে নিজেদের ধ্বংসে নিক্ষেপ করো না।",
    "source": "সূরা বাকারা, আয়াত ১৯৫",
    "topic": "health",
    "duaCategory": null,
    "stepAssignment": 25,
    "relatedContentIds": ["ic_024", "ic_026"]
  },
  {
    "id": "ic_026",
    "type": "hadith",
    "arabicText": "الْمُؤْمِنُ الْقَوِيُّ خَيْرٌ وَأَحَبُّ إِلَى اللَّهِ مِنَ الْمُؤْمِنِ الضَّعِيفِ",
    "banglaTransliteration": "আলমু'মিনুল কাওয়িয়্যু খাইরুন ওয়া আহাব্বু ইলাল্লাহি মিনাল মু'মিনিদ দাইফ",
    "banglaTranslation": "শক্তিশালী মুমিন দুর্বল মুমিনের চেয়ে উত্তম এবং আল্লাহর কাছে বেশি প্রিয়।",
    "source": "সহিহ মুসলিম, হাদিস ২৬৬৪",
    "topic": "health",
    "duaCategory": null,
    "stepAssignment": 26,
    "relatedContentIds": ["ic_024", "ic_027"]
  },
  {
    "id": "ic_027",
    "type": "ayah",
    "arabicText": "وَلَا تُسْرِفُوا إِنَّهُ لَا يُحِبُّ الْمُسْرِفِينَ",
    "banglaTransliteration": "ওয়া লা তুসরিফু ইন্নাহু লা ইউহিব্বুল মুসরিফিন",
    "banglaTranslation": "অপব্যয় করো না, নিশ্চয়ই তিনি অপব্যয়কারীদের পছন্দ করেন না।",
    "source": "সূরা আনআম, আয়াত ১৪১",
    "topic": "health",
    "duaCategory": null,
    "stepAssignment": 27,
    "relatedContentIds": ["ic_025", "ic_028"]
  },
  {
    "id": "ic_028",
    "type": "hadith",
    "arabicText": "لَا ضَرَرَ وَلَا ضِرَارَ",
    "banglaTransliteration": "লা দারারা ওয়া লা দিরার",
    "banglaTranslation": "নিজের ক্ষতি করা যাবে না এবং অন্যের ক্ষতি করা যাবে না।",
    "source": "ইবনে মাজাহ, হাদিস ২৩৪০",
    "topic": "health",
    "duaCategory": null,
    "stepAssignment": 28,
    "relatedContentIds": ["ic_025", "ic_029"]
  },
  {
    "id": "ic_029",
    "type": "ayah",
    "arabicText": "وَكُلُوا وَاشْرَبُوا وَلَا تُسْرِفُوا",
    "banglaTransliteration": "ওয়া কুলু ওয়াশরাবু ওয়া লা তুসরিফু",
    "banglaTranslation": "খাও এবং পান করো, কিন্তু অপব্যয় করো না।",
    "source": "সূরা আরাফ, আয়াত ৩১",
    "topic": "health",
    "duaCategory": null,
    "stepAssignment": 29,
    "relatedContentIds": ["ic_027", "ic_030"]
  },
  {
    "id": "ic_030",
    "type": "hadith",
    "arabicText": "سَلِ اللَّهَ الْعَفْوَ وَالْعَافِيَةَ فَإِنَّ أَحَدًا لَمْ يُعْطَ بَعْدَ الْيَقِينِ خَيْرًا مِنَ الْعَافِيَةِ",
    "banglaTransliteration": "সালিল্লাহাল আফওয়া ওয়াল আফিয়াতা ফাইন্না আহাদান লাম ইউতা বাআদাল ইয়াকিনি খাইরান মিনাল আফিয়াহ",
    "banglaTranslation": "আল্লাহর কাছে ক্ষমা ও সুস্বাস্থ্য চাও। ঈমানের পর সুস্বাস্থ্যের চেয়ে উত্তম কোনো নেয়ামত কাউকে দেওয়া হয়নি।",
    "source": "তিরমিযি, হাদিস ৩৫৫৮",
    "topic": "health",
    "duaCategory": null,
    "stepAssignment": 30,
    "relatedContentIds": ["ic_022", "ic_029"]
  },
  {
    "id": "ic_031",
    "type": "ayah",
    "arabicText": "وَهُوَ الَّذِي يَقْبَلُ التَّوْبَةَ عَنْ عِبَادِهِ وَيَعْفُو عَنِ السَّيِّئَاتِ",
    "banglaTransliteration": "ওয়া হুওয়াল্লাযি ইয়াকবালুত তাওবাতা আন ইবাদিহি ওয়া ইয়াআফু আনিস সাইয়িআত",
    "banglaTranslation": "তিনিই তাঁর বান্দাদের তাওবা কবুল করেন এবং পাপ মাফ করেন।",
    "source": "সূরা শুরা, আয়াত ২৫",
    "topic": "tawbah",
    "duaCategory": null,
    "stepAssignment": 31,
    "relatedContentIds": ["ic_032", "ic_034"]
  },
  {
    "id": "ic_032",
    "type": "ayah",
    "arabicText": "إِنَّ اللَّهَ يُحِبُّ التَّوَّابِينَ وَيُحِبُّ الْمُتَطَهِّرِينَ",
    "banglaTransliteration": "ইন্নাল্লাহা ইউহিব্বুত তাওয়াবিনা ওয়া ইউহিব্বুল মুতাতাহহিরিন",
    "banglaTranslation": "নিশ্চয়ই আল্লাহ তাওবাকারীদের ভালোবাসেন এবং পবিত্রতা অর্জনকারীদের ভালোবাসেন।",
    "source": "সূরা বাকারা, আয়াত ২২২",
    "topic": "tawbah",
    "duaCategory": null,
    "stepAssignment": 32,
    "relatedContentIds": ["ic_031", "ic_033"]
  },
  {
    "id": "ic_033",
    "type": "hadith",
    "arabicText": "كُلُّ بَنِي آدَمَ خَطَّاءٌ وَخَيْرُ الْخَطَّائِينَ التَّوَّابُونَ",
    "banglaTransliteration": "কুল্লু বানি আদামা খাত্তাউন ওয়া খাইরুল খাত্তাইনাত তাওয়াবুন",
    "banglaTranslation": "প্রতিটি আদম সন্তানই ভুল করে, আর ভুলকারীদের মধ্যে সর্বোত্তম হলো তারা যারা তাওবা করে।",
    "source": "তিরমিযি, হাদিস ২৪৯৯",
    "topic": "tawbah",
    "duaCategory": null,
    "stepAssignment": 33,
    "relatedContentIds": ["ic_031", "ic_035"]
  },
  {
    "id": "ic_034",
    "type": "ayah",
    "arabicText": "وَمَن يَعْمَلْ سُوءًا أَوْ يَظْلِمْ نَفْسَهُ ثُمَّ يَسْتَغْفِرِ اللَّهَ يَجِدِ اللَّهَ غَفُورًا رَّحِيمًا",
    "banglaTransliteration": "ওয়া মাইঁ ইয়াআমাল সু'আন আও ইয়াযলিম নাফসাহু সুম্মা ইয়াসতাগফিরিল্লাহা ইয়াজিদিল্লাহা গাফুরার রাহিমা",
    "banglaTranslation": "যে মন্দ কাজ করে বা নিজের উপর জুলুম করে, তারপর আল্লাহর কাছে ক্ষমা চায়, সে আল্লাহকে ক্ষমাশীল ও দয়ালু পাবে।",
    "source": "সূরা নিসা, আয়াত ১১০",
    "topic": "tawbah",
    "duaCategory": null,
    "stepAssignment": 34,
    "relatedContentIds": ["ic_031", "ic_036"]
  },
  {
    "id": "ic_035",
    "type": "hadith",
    "arabicText": "إِنَّ اللَّهَ يَبْسُطُ يَدَهُ بِاللَّيْلِ لِيَتُوبَ مُسِيءُ النَّهَارِ وَيَبْسُطُ يَدَهُ بِالنَّهَارِ لِيَتُوبَ مُسِيءُ اللَّيْلِ",
    "banglaTransliteration": "ইন্নাল্লাহা ইয়াবসুতু ইয়াদাহু বিল্লাইলি লিইয়াতুবা মুসিউন নাহারি ওয়া ইয়াবসুতু ইয়াদাহু বিন নাহারি লিইয়াতুবা মুসিউল লাইল",
    "banglaTranslation": "আল্লাহ রাতে তাঁর হাত প্রসারিত করেন যাতে দিনের পাপী তাওবা করতে পারে, এবং দিনে হাত প্রসারিত করেন যাতে রাতের পাপী তাওবা করতে পারে।",
    "source": "সহিহ মুসলিম, হাদিস ২৭৫৯",
    "topic": "tawbah",
    "duaCategory": null,
    "stepAssignment": 35,
    "relatedContentIds": ["ic_033", "ic_037"]
  },
  {
    "id": "ic_036",
    "type": "ayah",
    "arabicText": "قُلْ يَا عِبَادِيَ الَّذِينَ أَسْرَفُوا عَلَىٰ أَنفُسِهِمْ لَا تَقْنَطُوا مِن رَّحْمَةِ اللَّهِ إِنَّ اللَّهَ يَغْفِرُ الذُّنُوبَ جَمِيعًا",
    "banglaTransliteration": "কুল ইয়া ইবাদিয়াল্লাযিনা আসরাফু আলা আনফুসিহিম লা তাকনাতু মির রাহমাতিল্লাহ ইন্নাল্লাহা ইয়াগফিরুয যুনুবা জামিআ",
    "banglaTranslation": "বলো: হে আমার বান্দারা যারা নিজেদের উপর অত্যাচার করেছ, আল্লাহর রহমত থেকে নিরাশ হয়ো না। নিশ্চয়ই আল্লাহ সকল পাপ মাফ করেন।",
    "source": "সূরা যুমার, আয়াত ৫৩",
    "topic": "tawbah",
    "duaCategory": null,
    "stepAssignment": 36,
    "relatedContentIds": ["ic_034", "ic_038"]
  },
  {
    "id": "ic_037",
    "type": "hadith",
    "arabicText": "التَّائِبُ مِنَ الذَّنْبِ كَمَنْ لَا ذَنْبَ لَهُ",
    "banglaTransliteration": "আত তাইবু মিনায যানবি কামান লা যানবা লাহু",
    "banglaTranslation": "পাপ থেকে তাওবাকারী ব্যক্তি এমন যেন তার কোনো পাপই নেই।",
    "source": "ইবনে মাজাহ, হাদিস ৪২৫০",
    "topic": "tawbah",
    "duaCategory": null,
    "stepAssignment": 37,
    "relatedContentIds": ["ic_033", "ic_036"]
  },
  {
    "id": "ic_038",
    "type": "ayah",
    "arabicText": "وَتُوبُوا إِلَى اللَّهِ جَمِيعًا أَيُّهَ الْمُؤْمِنُونَ لَعَلَّكُمْ تُفْلِحُونَ",
    "banglaTransliteration": "ওয়া তুবু ইলাল্লাহি জামিআন আইয়্যুহাল মু'মিনুনা লাআল্লাকুম তুফলিহুন",
    "banglaTranslation": "হে মুমিনগণ! তোমরা সকলে আল্লাহর কাছে তাওবা করো, যাতে তোমরা সফল হতে পারো।",
    "source": "সূরা নূর, আয়াত ৩১",
    "topic": "tawbah",
    "duaCategory": null,
    "stepAssignment": 38,
    "relatedContentIds": ["ic_032", "ic_037"]
  },
  {
    "id": "ic_039",
    "type": "hadith",
    "arabicText": "مَنْ أَحَبَّ لِقَاءَ اللَّهِ أَحَبَّ اللَّهُ لِقَاءَهُ",
    "banglaTransliteration": "মান আহাব্বা লিকাআল্লাহি আহাব্বাল্লাহু লিকাআহু",
    "banglaTranslation": "যে আল্লাহর সাথে সাক্ষাৎ পছন্দ করে, আল্লাহও তার সাথে সাক্ষাৎ পছন্দ করেন।",
    "source": "সহিহ বুখারি, হাদিস ৬৫০৭",
    "topic": "tawbah",
    "duaCategory": null,
    "stepAssignment": 39,
    "relatedContentIds": ["ic_036", "ic_040"]
  },
  {
    "id": "ic_040",
    "type": "ayah",
    "arabicText": "إِنَّ الَّذِينَ قَالُوا رَبُّنَا اللَّهُ ثُمَّ اسْتَقَامُوا تَتَنَزَّلُ عَلَيْهِمُ الْمَلَائِكَةُ",
    "banglaTransliteration": "ইন্নাল্লাযিনা কালু রাব্বুনাল্লাহু সুম্মাস তাকামু তাতানায্যালু আলাইহিমুল মালাইকাহ",
    "banglaTranslation": "যারা বলে আমাদের প্রতিপালক আল্লাহ, তারপর অবিচল থাকে, তাদের উপর ফেরেশতারা অবতীর্ণ হয়।",
    "source": "সূরা ফুসিলাত, আয়াত ৩০",
    "topic": "tawbah",
    "duaCategory": null,
    "stepAssignment": 40,
    "relatedContentIds": ["ic_038", "ic_041"]
  },
  {
    "id": "ic_041",
    "type": "ayah",
    "arabicText": "وَالَّذِينَ آمَنُوا وَعَمِلُوا الصَّالِحَاتِ لَنُكَفِّرَنَّ عَنْهُمْ سَيِّئَاتِهِمْ وَلَنَجْزِيَنَّهُمْ أَحْسَنَ الَّذِي كَانُوا يَعْمَلُونَ",
    "banglaTransliteration": "ওয়াল্লাযিনা আমানু ওয়া আমিলুস সালিহাতি লানুকাফফিরান্না আনহুম সাইয়িআতিহিম ওয়া লানাজযিয়ান্নাহুম আহসানাল্লাযি কানু ইয়াআমালুন",
    "banglaTranslation": "যারা ঈমান আনে ও সৎকাজ করে, আমি অবশ্যই তাদের পাপ মোচন করব এবং তারা যা করত তার চেয়ে উত্তম পুরস্কার দেব।",
    "source": "সূরা আনকাবুত, আয়াত ৭",
    "topic": "tawbah",
    "duaCategory": null,
    "stepAssignment": 41,
    "relatedContentIds": ["ic_039", "ic_040"]
  }
]
